rellipsoid/__init__.py
rellipsoid/rellipsoid.py
rellipsoid/test_rellipsoid.py
rellipsoid-0.0.1.dist-info/METADATA
rellipsoid-0.0.1.dist-info/WHEEL
rellipsoid-0.0.1.dist-info/top_level.txt
rellipsoid-0.0.1.dist-info/RECORD
