Metadata-Version: 2.1
Name: rellipsoid
Version: 0.0.1
Summary: Ellipsoidal model of planet with WSG84 values for Earth
Home-page: https://github.com/raabrp/rellipsoid
Author: Reilly Raab
Author-email: raabrp@gmail.com
License: UNKNOWN
Platform: UNKNOWN
Classifier: Programming Language :: Python :: 3
Classifier: License :: OSI Approved :: MIT License
Classifier: Operating System :: OS Independent
